odoo/addons/repair_payment_term/README.rst
odoo/addons/repair_payment_term/__init__.py
odoo/addons/repair_payment_term/__manifest__.py
odoo/addons/repair_payment_term/i18n/pt_BR.po
odoo/addons/repair_payment_term/i18n/repair_payment_term.pot
odoo/addons/repair_payment_term/models/__init__.py
odoo/addons/repair_payment_term/models/repair_order.py
odoo/addons/repair_payment_term/readme/CONFIGURE.rst
odoo/addons/repair_payment_term/readme/CONTRIBUTORS.rst
odoo/addons/repair_payment_term/readme/CREDITS.rst
odoo/addons/repair_payment_term/readme/DESCRIPTION.rst
odoo/addons/repair_payment_term/readme/USAGE.rst
odoo/addons/repair_payment_term/report/repair_report_templates.xml
odoo/addons/repair_payment_term/static/description/icon.png
odoo/addons/repair_payment_term/static/description/index.html
odoo/addons/repair_payment_term/tests/__init__.py
odoo/addons/repair_payment_term/tests/test_repair.py
odoo/addons/repair_payment_term/views/repair_order.xml
odoo12_addon_repair_payment_term-12.0.1.0.1.dist-info/METADATA
odoo12_addon_repair_payment_term-12.0.1.0.1.dist-info/WHEEL
odoo12_addon_repair_payment_term-12.0.1.0.1.dist-info/top_level.txt
odoo12_addon_repair_payment_term-12.0.1.0.1.dist-info/RECORD
